Workbook

Sheet Summary
A2: El Sereno construction takeoff
A3: 2340 El Sereno Ave, Altadena, CA 91001
A5: Trade | B5: Primary quantity | C5: Quantity | D5: Unit | E5: Basis / limitation
A6: Foundation | B6: Continuous footings | C6: ='Building quantities'!C13 -> 231.91667 | D6: LF | E6: Approx. trace; 12 in x 24 in
A7: Foundation | B7: Slab-on-grade area | C7: ='Building quantities'!C17 -> 1623.75 | D7: SF | E7: House dimensions + 400 SF garage + 33 SF porch
A8: Foundation | B8: 4 in slab concrete, gross | C8: ='Building quantities'!C18 -> 20.046296 | D8: CY | E8: Footing overlap not deducted
A9: Foundation | B9: Footing concrete, gross | C9: ='Building quantities'!C14 -> 17.179012 | D9: CY | E9: Pads separate; no combined pour total
A10: Framing | B10: Floor joists | C10: ='Building quantities'!C23 -> 0 | D10: SF | E10: Slab-on-grade; none shown
A11: Framing | B11: Ceiling framing | C11: ='Building quantities'!C27 -> 1623.75 | D11: SF | E11: House + garage + provisional porch
A12: Framing | B12: Wall framing, gross one face | C12: ='Building quantities'!C32 -> 3126.75 | D12: SF | E12: Includes partitions, gables and openings
A13: Drywall | B13: Board / soffit face area, net | C13: ='Building quantities'!C51 -> 5081.75 | D13: SF | E13: Includes provisional garage / porch and wet walls
A14: Stucco | B14: Exterior net face area | C14: ='Building quantities'!C42 -> 1502.75 | D14: SF | E14: Gable geometry estimate; returns excluded
A15: Roofing | B15: Sloped roof surface, net | C15: ='Building quantities'!C34 -> 2066.8436 | D15: SF | E15: Scaled A-5 roof outline at 4:12
A16: Roofing | B16: Shingles + 10% waste | C16: ='Building quantities'!C35 -> 22.73528 | D16: SQ | E16: One square = 100 SF
A17: Floor coverings | B17: House usable floor, approx. | C17: ='Building quantities'!C53 -> 1069.0799 | D17: SF | E17: Finish types unspecified
A18: Floor coverings | B18: Bath tile allowance | C18: ='Building quantities'!C54 -> 70 | D18: SF | E18: Included in house usable floor
A19: Floor coverings | B19: Other unassigned floor finish | C19: ='Building quantities'!C55 -> 999.07986 | D19: SF | E19: Included in house usable floor
A22: MEP scope | B22: Plan count / requirement | C22: Quantity | D22: Unit | E22: Status
A23: Electrical | B23: 225 amp service | C23: 1 | D23: EA | E23: Shown on A-4
A24: Electrical | B24: Smoke / carbon monoxide symbols | C24: 4 / 4 | D24: EA | E24: One additional bedroom smoke alarm allowed
A25: Electrical | B25: Receptacles / lights / switches | C25: See MEP | D25: EA | E25: Budget allowances; no device layout
A26: Plumbing | B26: WC / lavatory / shower | C26: 2 / 2 / 2 | D26: EA | E26: Drawn fixtures
A27: Plumbing | B27: Kitchen / garage sinks | C27: 1 / 1 | D27: EA | E27: Drawn fixtures
A28: Plumbing | B28: Water heater | C28: 1 | D28: EA | E28: Tankless vs 80 gal heat pump conflict
A29: Mechanical | B29: Heat-pump system | C29: 1 | D29: system | E29: Ductless vs attic FAU conflict
A30: Mechanical | B30: Bath fans / hood | C30: 2 / 1 | D30: EA | E30: 73 CFM bath fans / 250 CFM hood
A31: Mechanical | B31: Whole-house ventilation | C31: 73 | D31: CFM | E31: May share a bath fan; extra fan TBD
A34: Resolve before ordering: 1,222 SF title vs 1,190.75 SF dimensions; water heater and HVAC equipment conflicts.
A35: Measured quantities, plan counts and allowances are labeled. Waste is shown separately in Building quantities. No pricing included.

Sheet Building quantities
A2: El Sereno construction quantities
A3: Net quantities exclude listed waste. Gross framing includes openings.
A5: Trade | B5: Item | C5: Quantity | D5: Unit | E5: Basis | F5: Drawing / calculation
A6: Area | B6: House footprint | C6: =Measurements!B41 -> 1190.75 | D6: SF | E6: Dimensioned | F6: A-4 p4. Title says 1,222 SF; dimensions give 1,190.75 SF.
A7: Area | B7: Garage footprint | C7: =Measurements!B7*Measurements!B8 -> 400 | D7: SF | E7: Dimensioned | F7: 20 ft x 20 ft
A8: Area | B8: Covered porch | C8: =Measurements!B10 -> 33 | D8: SF | E8: Plan stated | F8: Title area retained; dimension product is 31.60 SF
A9: Foundation | B9: House continuous footing | C9: =Measurements!B37 -> 138.16667 | D9: LF | E9: Dimensioned trace | F9: S-1 p10, full house perimeter including shared garage line
A10: Foundation | B10: Garage additional footing | C10: =Measurements!B39 -> 65.166667 | D10: LF | E10: Dimensioned trace | F10: S-1 p10, no duplicate shared house / garage line
A11: Foundation | B11: Interior bearing footing | C11: =Measurements!B16 -> 17.333333 | D11: LF | E11: Scaled | F11: S-1, master-bedroom south wall
A12: Foundation | B12: Porch additional footing | C12: =Measurements!B11+Measurements!B12 -> 11.25 | D12: LF | E12: Dimensioned trace | F12: S-1, west and front porch edges; other edges already included
A13: Foundation | B13: Total continuous footing | C13: =SUM(C9:C12) -> 231.91667 | D13: LF | E13: Calculated | F13: Nominal 12 in wide x 24 in deep
A14: Foundation | B14: Continuous footing concrete (gross) | C14: ='Building quantities'!C13*Measurements!B17*Measurements!B18/27 -> 17.179012 | D14: CY | E14: Calculated | F14: Excludes pads; gross volume before slab overlap adjustment
A15: Foundation | B15: P2.0 isolated pads | C15: 2 | D15: EA | E15: Counted | F15: S-1 p10, one internal and one outside east wall; 2 ft x 2 ft x 24 in
A16: Foundation | B16: Pad concrete (gross) | C16: ='Building quantities'!C15*2*2*2/27 -> 0.59259259 | D16: CY | E16: Calculated | F16: Do not combine with slab without intersection adjustment
A17: Foundation | B17: Slab footprint including porch | C17: =SUM(C6:C8) -> 1623.75 | D17: SF | E17: Calculated | F17: S-1, slab-on-grade throughout
A18: Foundation | B18: 4 in slab concrete (gross) | C18: ='Building quantities'!C17*Measurements!B19/27 -> 20.046296 | D18: CY | E18: Calculated | F18: Separate gross quantity; no combined footing + slab pour total
A19: Foundation | B19: 6 mil under-slab vapor barrier | C19: ='Building quantities'!C17 -> 1623.75 | D19: SF | E19: Plan stated / calculated | F19: S-1. Add laps after roll selection.
A20: Foundation | B20: Sand layers total 4 in | C20: ='Building quantities'!C17*4/12/27 -> 20.046296 | D20: CY | E20: Plan stated / calculated | F20: S-1: 2 in sand above + 2 in below membrane
A21: Foundation | B21: Footing #4 longitudinal bars | C21: ='Building quantities'!C13*4 -> 927.66667 | D21: LF | E21: Calculated | F21: 2 top + 2 bottom; excludes laps, bends, hooks
A22: Foundation | B22: Slab #4 at 16 in each way (area method) | C22: ='Building quantities'!C17*2/(16/12) -> 2435.625 | D22: LF | E22: Approximate | F22: S-1. Area / spacing method; final edge bars and laps not included.
A23: Framing | B23: Floor joist area | C23: 0 | D23: SF | E23: Not shown | F23: S-1 / A-7: slab-on-grade; no raised floor framing
A24: Framing | B24: House ceiling joist area | C24: ='Building quantities'!C6 -> 1190.75 | D24: SF | E24: Dimensioned footprint | F24: S-2 p11: CJ1 2x10 at 16 in OC
A25: Framing | B25: Garage ceiling joist area | C25: ='Building quantities'!C7 -> 400 | D25: SF | E25: Dimensioned footprint | F25: S-2: CJ1 2x10 at 16 in OC
A26: Framing | B26: Porch ceiling framing area | C26: ='Building quantities'!C8 -> 33 | D26: SF | E26: Provisional | F26: Covered porch footprint; final member layout to be confirmed
A27: Framing | B27: Total ceiling framing area | C27: =SUM(C24:C26) -> 1623.75 | D27: SF | E27: Calculated | F27: Area coverage only, not lumber lineal feet
A28: Framing | B28: House perimeter walls, gross one face | C28: =Measurements!B37*Measurements!B13 -> 1105.3333 | D28: SF | E28: Calculated | F28: Includes shared house / garage wall once
A29: Framing | B29: Garage additional walls, gross one face | C29: =Measurements!B39*Measurements!B14 -> 553.91667 | D29: SF | E29: Calculated | F29: Garage perimeter less shared house / garage wall
A30: Framing | B30: Interior partitions, gross one face | C30: =Measurements!B36*Measurements!B13 -> 1219.3333 | D30: SF | E30: Scaled / calculated | F30: A-4 and S-2; 152.42 LF traced; includes openings
A31: Framing | B31: Gable walls, gross one face | C31: =2*0.5*Measurements!B5*(Measurements!B5/2*Measurements!B20/Measurements!B21)+2*0.5*Measurements!B7*(Measurements!B7/2*Measurements!B20/Measurements!B21) -> 248.16667 | D31: SF | E31: Geometry estimate | F31: A-6 / A-7, two house and two garage gable ends
A32: Framing | B32: Total wall framing, gross one face | C32: =SUM(C28:C31) -> 3126.75 | D32: SF | E32: Calculated | F32: House + garage + partitions + gables; openings remain in gross area
A33: Roofing | B33: Roof horizontal projection | C33: =Measurements!B22 -> 1960.78 | D33: SF | E33: Scaled trace | F33: A-5 p5; includes eaves and east roof extension
A34: Roofing | B34: Roof sloped surface, net | C34: ='Building quantities'!C33*Measurements!B43 -> 2066.8436 | D34: SF | E34: Scaled / calculated | F34: 4:12 slope factor; approximate traced roof outline
A35: Roofing | B35: Class A shingles including 10% waste | C35: ='Building quantities'!C34*(1+Measurements!B23)/100 -> 22.73528 | D35: SQ | E35: Order allowance | F35: 1 roofing square = 100 SF. Round to supplier packages.
A36: Roofing | B36: Underlayment, net | C36: ='Building quantities'!C34 -> 2066.8436 | D36: SF | E36: Scaled / calculated | F36: Laps and roll coverage not included
A37: Roofing | B37: 1/2 in CDX roof sheathing | C37: =ROUNDUP('Building quantities'!C34*(1+Measurements!B23)/32,0) -> 72 | D37: 4x8 sheets | E37: Order allowance | F37: S-2 roof diaphragm note; 10% waste
A38: Roofing | B38: Gable vents | C38: 4 | D38: EA | E38: Plan note | F38: A-5 note: four vents; A-5 / A-6 dimensions conflict
A39: Stucco | B39: Exposed exterior wall body, gross | C39: =(Measurements!B37-Measurements!B38)*Measurements!B13+Measurements!B39*Measurements!B14 -> 1540.5833 | D39: SF | E39: Calculated | F39: A-4 / A-6, excludes shared garage wall
A40: Stucco | B40: Stucco including gables, gross | C40: ='Building quantities'!C39+'Building quantities'!C31 -> 1788.75 | D40: SF | E40: Calculated | F40: 7/8 in Portland cement plaster noted on A-6
A41: Stucco | B41: Window and external door deductions | C41: =Measurements!B32+Measurements!B33+Measurements!B35 -> 286 | D41: SF | E41: Count / schedule | F41: A-4 schedules; opening returns and vents excluded
A42: Stucco | B42: Stucco net face area | C42: ='Building quantities'!C40-'Building quantities'!C41 -> 1502.75 | D42: SF | E42: Calculated estimate | F42: Includes gable geometry allowance
A43: Stucco | B43: Stucco / lath / WRB area + 5% | C43: ='Building quantities'!C42*(1+Measurements!B25) -> 1577.8875 | D43: SF | E43: Allowance | F43: A-6 WRB and wire lath; specify layers / laps separately
A44: Stucco | B44: Weep screed, gross perimeter | C44: =Measurements!B40 -> 188.5 | D44: LF | E44: Gross allowance | F44: Before deductions at doors and field termination details
A45: Drywall | B45: House perimeter walls, net inside face | C45: ='Building quantities'!C28-Measurements!B32-Measurements!B33-Measurements!B34 -> 908.22222 | D45: SF | E45: Calculated estimate | F45: 8 ft wall height; garage-side face measured separately
A46: Drywall | B46: Interior partitions, net both faces | C46: =2*'Building quantities'!C30-2*Measurements!B30*Measurements!B31 -> 1994.2222 | D46: SF | E46: Scaled / calculated | F46: Deducts door gaps on both sides; closet faces included
A47: Drywall | B47: Garage walls, net inside face | C47: =2*(Measurements!B7+Measurements!B8)*Measurements!B14-Measurements!B35-Measurements!B34 -> 555.55556 | D47: SF | E47: Provisional finish scope | F47: 8 ft 6 in garage height. Rating / thickness to be resolved.
A48: Drywall | B48: House ceiling area | C48: ='Building quantities'!C6 -> 1190.75 | D48: SF | E48: Gross footprint allowance | F48: Flat ceiling per A-7; no wall-footprint deduction
A49: Drywall | B49: Garage ceiling area | C49: ='Building quantities'!C7 -> 400 | D49: SF | E49: Provisional finish scope | F49: Verify required finish and protection
A50: Drywall | B50: Porch soffit / ceiling finish | C50: ='Building quantities'!C8 -> 33 | D50: SF | E50: Provisional finish scope | F50: Exterior approved finish, not ordinary interior board
A51: Drywall | B51: Total board / soffit face area, net | C51: =SUM(C45:C50) -> 5081.75 | D51: SF | E51: Calculated estimate | F51: Includes wet walls before backer-board substitution and provisional garage / porch
A52: Drywall | B52: Board / soffit face area + 10% | C52: ='Building quantities'!C51*(1+Measurements!B24) -> 5589.925 | D52: SF | E52: Order allowance | F52: Separate types before ordering; area does not set sheet lengths
A53: Floor coverings | B53: House usable floor, approximate | C53: ='Building quantities'!C6-Measurements!B37*Measurements!B27-Measurements!B36*Measurements!B28 -> 1069.0799 | D53: SF | E53: Approximate net | F53: Deducts estimated wall footprints. Cabinets / closets remain included.
A54: Floor coverings | B54: Bathroom tile allowance | C54: =Measurements!B29 -> 70 | D54: SF | E54: Finish allowance | F54: Two baths; exact finish and shower-floor inclusion unconfirmed
A55: Floor coverings | B55: Remaining unassigned floor covering | C55: ='Building quantities'!C53-'Building quantities'!C54 -> 999.07986 | D55: SF | E55: Finish allowance | F55: Bedroom, living, kitchen, hall and closet areas; finish unspecified
A56: Floor coverings | B56: Bath tile + 10% waste | C56: ='Building quantities'!C54*(1+Measurements!B26) -> 77 | D56: SF | E56: Order allowance | F56: Final tile format controls cutting loss
A57: Floor coverings | B57: Other flooring + 10% waste | C57: ='Building quantities'!C55*(1+Measurements!B26) -> 1098.9878 | D57: SF | E57: Order allowance | F57: Split into finish types when owner selects materials
A58: Floor coverings | B58: Garage usable concrete floor | C58: =(Measurements!B7-2*Measurements!B27)*(Measurements!B8-2*Measurements!B27) -> 370.5625 | D58: SF | E58: Approximate net | F58: No applied garage floor covering specified

Sheet MEP
A2: Electrical, plumbing and mechanical takeoff
A3: Counted symbols and equipment are distinguished from budget allowances.
A5: Trade | B5: Item | C5: Quantity | D5: Unit | E5: Basis | F5: Drawing / scope
A6: Electrical | B6: New service / main panel | C6: 1 | D6: EA | E6: Plan stated | F6: A-4 p4: new 225 amp service; panel circuit schedule not supplied
A7: Electrical | B7: Smoke alarms shown | C7: 4 | D7: EA | E7: Counted symbols | F7: A-4: northwest bedroom, middle west bedroom, master bedroom, living area
A8: Electrical | B8: Additional southwest bedroom smoke alarm | C8: 1 | D8: EA | E8: Allowance | F8: Bedroom has no SD symbol on A-4; verify final alarm layout
A9: Electrical | B9: Carbon monoxide alarms shown | C9: 4 | D9: EA | E9: Counted symbols | F9: A-4: same four locations as visible SD symbols
A10: Electrical | B10: Bedroom general duplex receptacles | C10: 16 | D10: EA | E10: Budget allowance | F10: Four per bedroom x four bedrooms; no receptacle plan
A11: Electrical | B11: Living / dining general duplex receptacles | C11: 6 | D11: EA | E11: Budget allowance | F11: No receptacle plan
A12: Electrical | B12: Hall general duplex receptacles | C12: 2 | D12: EA | E12: Budget allowance | F12: No receptacle plan
A13: Electrical | B13: Kitchen countertop receptacles | C13: 6 | D13: EA | E13: Budget allowance | F13: GFCI protection allowance; final countertop / island layout required
A14: Electrical | B14: Bathroom receptacles | C14: 2 | D14: EA | E14: Budget allowance | F14: One per bathroom; GFCI protection allowance
A15: Electrical | B15: Garage receptacles | C15: 4 | D15: EA | E15: Budget allowance | F15: GFCI protection allowance; equipment outlets below are separate
A16: Electrical | B16: Exterior weather-resistant receptacles | C16: 2 | D16: EA | E16: Budget allowance | F16: GFCI / weather protection allowance; front and rear
A17: Electrical | B17: Laundry receptacle | C17: 1 | D17: EA | E17: Budget allowance | F17: W/D area A-4; final circuit / GFCI protection to be confirmed
... A37: Electrical | B37: Switch / dimmer / sensor locations | C37: 18 | D37: EA | E37: Budget allowance | F37: Room / closet / exterior controls; no switch plan
A38: Electrical | B38: Three-way switches | C38: TBD | D38: EA | E38: Not scheduled | F38: No switching layout. Included locations above do not define three-way device counts.
A39: Electrical | B39: AFCI circuit protection | C39: TBD | D39: circuits | E39: Not scheduled | F39: Circuit schedule missing; protected outlets are not extra devices
A40: Electrical | B40: GFCI circuit protection | C40: TBD | D40: circuits | E40: Not scheduled | F40: Protection may be at breaker or receptacle; do not double-count
A41: Electrical | B41: Branch wire / conduit / feeders | C41: TBD | D41: LF | E41: Not measurable | F41: Routes, circuit schedule, conductor sizes and service distance missing
A42: Plumbing | B42: Water closets | C42: 2 | D42: EA | E42: Counted fixtures | F42: A-4: one per bathroom; generic note says (4), conflicts with two drawn
A43: Plumbing | B43: Bathroom lavatories | C43: 2 | D43: EA | E43: Counted fixtures | F43: A-4: one per bathroom
A44: Plumbing | B44: Showers / shower valves | C44: 2 | D44: EA | E44: Counted fixtures | F44: A-4: two shower footprints; tub not shown
A45: Plumbing | B45: Kitchen sink | C45: 1 | D45: EA | E45: Counted fixtures | F45: A-4: double-bowl sink, counted as one fixture
A46: Plumbing | B46: Garage utility sink | C46: 1 | D46: EA | E46: Counted fixtures | F46: A-4, west garage wall
A47: Plumbing | B47: Washer rough-in box / standpipe | C47: 1 | D47: set | E47: Equipment counted | F47: A-4 W/D; box / standpipe detail not supplied
A48: Plumbing | B48: Dishwasher water / drain connection | C48: 1 | D48: set | E48: Budget allowance | F48: Dishwasher not labeled; kitchen appliance allowance
A49: Plumbing | B49: Exterior hose bibs | C49: 2 | D49: EA | E49: Budget allowance | F49: Legend only; no clearly located HB symbols
A50: Plumbing | B50: Tankless water heater (alternate A) | C50: 1 | D50: EA | E50: Plan stated / conflict | F50: A-4 exterior west wall. Alternate to heat-pump heater; do not add both.
A51: Plumbing | B51: 80 gal heat-pump water heater (alternate B) | C51: 1 | D51: EA | E51: Energy schedule / conflict | F51: T24 Sheet 2 p17: one outdoor unit. Alternate to A-4 tankless.
A52: Plumbing | B52: Water heater connection package | C52: 1 | D52: set | E52: Equipment counted | F52: Hot / cold, shutoff, relief discharge; drain requirements depend on selected heater
A53: Plumbing | B53: Water supply rough-in | C53: 1 | D53: lot | E53: Scope allowance | F53: 2 WC, 2 lavs, 2 showers, kitchen sink, utility sink, washer; fixture route lengths TBD
A54: Plumbing | B54: Drain / waste / vent rough-in | C54: 1 | D54: lot | E54: Scope allowance | F54: Same nine fixture / appliance locations; dishwasher added allowance
A55: Plumbing | B55: Hot / cold pipe by size | C55: TBD | D55: LF | E55: Not measurable | F55: No pipe layout / riser; do not infer purchase lengths
A56: Plumbing | B56: DWV pipe by size | C56: TBD | D56: LF | E56: Not measurable | F56: No pipe layout / riser; sewer connection route missing
A57: Plumbing | B57: Gas system / seismic shutoff | C57: 1 | D57: lot | E57: Plan note / conflict | F57: A-4 seismic shutoff note; connected appliance fuel choices unresolved
A58: Plumbing | B58: Gas piping by size | C58: TBD | D58: LF | E58: Not measurable | F58: Meter location / routing / appliance loads not scheduled
A59: Mechanical | B59: Ductless variable-capacity heat-pump system | C59: 1 | D59: system | E59: Energy schedule | F59: T24 Sheet 2 p17: approximately 22,000 BTU/h cooling; confirm equipment model
A60: Mechanical | B60: Indoor ductless heads | C60: TBD | D60: EA | E60: Not scheduled | F60: One heating / cooling system does not establish indoor head count
A61: Mechanical | B61: Attic FAU / hall return (conflicting alternate) | C61: 1 | D61: system | E61: Plan stated / conflict | F61: A-4. Alternate to ductless equipment; do not add both systems.
A62: Mechanical | B62: HVAC refrigerant line sets / drains | C62: TBD | D62: LF | E62: Not measurable | F62: Indoor equipment locations / routes not supplied
A63: Mechanical | B63: Supply ducts / registers / return grille | C63: TBD | D63: LF / EA | E63: Not scheduled | F63: Only applies if ducted alternate is selected
A64: Mechanical | B64: Bathroom exhaust fans | C64: 2 | D64: EA | E64: Counted symbols | F64: A-4: two fans; legend 73 CFM each
A65: Mechanical | B65: Kitchen exhaust hood | C65: 1 | D65: EA | E65: Plan stated | F65: A-4: 250 CFM; hood / duct size to be selected
A66: Mechanical | B66: Whole-house ventilation requirement | C66: 73 | D66: CFM | E66: Plan stated | F66: A-4 IAQ and T24 p17: 73 CFM exhaust. May be integrated with a bathroom fan.
A67: Mechanical | B67: Additional dedicated IAQ fan | C67: TBD | D67: EA | E67: Not scheduled | F67: Avoid double-counting a bath fan used for continuous ventilation
A68: Mechanical | B68: Dryer exhaust connection | C68: 1 | D68: set | E68: Equipment counted | F68: W/D shown; ventless dryer choice may remove duct
A69: Mechanical | B69: Exhaust duct lengths / terminations | C69: TBD | D69: LF / EA | E69: Not measurable | F69: Bath / hood / dryer routes and discharge points not drawn

Sheet Measurements
A2: El Sereno measurements and assumptions
A4: Input / calculation | B4: Value | C4: Unit | D4: Basis | E4: Drawing / explanation
A5: House width | B5: 33 | C5: LF | D5: Dimension | E5: A-4, PDF p4
A6: House length | B6: 36.083333 | C6: LF | D6: Dimension | E6: A-4, PDF p4: 36 ft 1 in
A7: Garage width | B7: 20 | C7: LF | D7: Dimension | E7: A-4, PDF p4
A8: Garage length | B8: 20 | C8: LF | D8: Dimension | E8: A-4, PDF p4
A9: Garage offset from house west wall | B9: 18.166667 | C9: LF | D9: Dimension | E9: A-4, PDF p4
A10: Porch stated area | B10: 33 | C10: SF | D10: Plan stated | E10: A-4 title; 5 ft 5 in x 5 ft 10 in = 31.60 SF
A11: Porch projection | B11: 5.8333333 | C11: LF | D11: Dimension | E11: A-4, PDF p4
A12: Porch width | B12: 5.4166667 | C12: LF | D12: Dimension | E12: A-4, PDF p4
A13: House wall height | B13: 8 | C13: FT | D13: Dimension | E13: A-7 section A-A, PDF p7
A14: Garage wall height | B14: 8.5 | C14: FT | D14: Dimension | E14: A-7 section B-B, PDF p7
A15: House stated floor area | B15: 1222 | C15: SF | D15: Plan stated | E15: A-1 through A-7 titles
A16: Main interior bearing footing | B16: 17.333333 | C16: LF | D16: Scaled | E16: S-1, PDF p10: master-bedroom south wall
... A35: Garage overhead door area | B35: 106.66667 | C35: SF | D35: Count / schedule | E35: A-4: D4 x1
A36: Interior wall length | B36: =SUM(B48:B64) -> 152.41667 | C36: LF | D36: Scaled gross | E36: Sum of traced partitions below; includes door gaps
A37: House perimeter | B37: =2*(B5+B6) -> 138.16667 | C37: LF | D37: Calculated | E37: Rectangular house outline
A38: Shared house / garage wall | B38: =B5-B9 -> 14.833333 | C38: LF | D38: Calculated | E38: House width less garage offset
A39: Garage additional wall length | B39: =2*(B7+B8)-B38 -> 65.166667 | C39: LF | D39: Calculated | E39: Garage perimeter less shared wall
A40: Exterior exposed perimeter | B40: =B37+2*(B7+B8)-2*B38 -> 188.5 | C40: LF | D40: Calculated | E40: House plus garage, deduct shared wall twice
A41: House dimensioned footprint | B41: =B5*B6 -> 1190.75 | C41: SF | D41: Calculated | E41: 33 ft x 36 ft 1 in
A42: House area discrepancy | B42: =B15-B41 -> 31.25 | C42: SF | D42: Calculated | E42: Title area less dimensioned footprint
A43: Roof slope factor | B43: =SQRT(1+(B20/B21)^2) -> 1.0540926 | C43: ratio | D43: Calculated | E43: Square root of 1 + (rise / run)^2
A46: Partition trace (gross length, includes openings)
A47: Wall segment | B47: Length | C47: Unit | D47: Basis | E47: Reference
A48: Hall west partition including door gaps | B48: 36.083333 | C48: LF | D48: Scaled | E48: A-4 / S-2; rounded to nearest inch or half foot
A49: Hall east upper partition | B49: 13.416667 | C49: LF | D49: Scaled | E49: A-4 / S-2; rounded to nearest inch or half foot
A50: Master bedroom south bearing wall | B50: 17.333333 | C50: LF | D50: Scaled | E50: A-4 / S-2; rounded to nearest inch or half foot
A51: Northwest bedroom south wall | B51: 11.916667 | C51: LF | D51: Scaled | E51: A-4 / S-2; rounded to nearest inch or half foot
A52: West bath south wall | B52: 11.916667 | C52: LF | D52: Scaled | E52: A-4 / S-2; rounded to nearest inch or half foot
A53: Southwest bedroom north wall | B53: 11.916667 | C53: LF | D53: Scaled | E53: A-4 / S-2; rounded to nearest inch or half foot
A54: West bath east wall | B54: 5 | C54: LF | D54: Scaled | E54: A-4 / S-2; rounded to nearest inch or half foot
A55: Northwest closet side | B55: 5.5833333 | C55: LF | D55: Scaled | E55: A-4 / S-2; rounded to nearest inch or half foot
A56: Northwest closet return | B56: 2.5 | C56: LF | D56: Scaled | E56: A-4 / S-2; rounded to nearest inch or half foot
A57: Master bath east wall | B57: 6.6666667 | C57: LF | D57: Scaled | E57: A-4 / S-2; rounded to nearest inch or half foot
A58: Master bath south wall | B58: 5.6666667 | C58: LF | D58: Scaled | E58: A-4 / S-2; rounded to nearest inch or half foot
A59: Master closet east wall | B59: 3.4166667 | C59: LF | D59: Scaled | E59: A-4 / S-2; rounded to nearest inch or half foot
... A64: Southwest closet return | B64: 2.5 | C64: LF | D64: Scaled | E64: A-4 / S-2; rounded to nearest inch or half foot
A68: Scope notes and items to resolve
A70: Source: El Sereno Approved stamped plans DWGS-UNC-BLDR250722008809-PCF(1).pdf, 18 pages. Project: 2340 El Sereno Ave, Altadena, CA 91001.
A71: Quantities are an estimating takeoff from the supplied architectural / structural / energy set. No prices included.
A72: Dimensioned house area is 1,190.75 SF; drawing titles say 1,222 SF. Resolve the 31.25 SF discrepancy before ordering slab, flooring or ceiling materials.
A73: Porch title is 33 SF; dimension product is 31.60 SF. This takeoff retains 33 SF for porch slab and ceiling.
A74: Gross framing SF measures one wall plane, including openings. Drywall SF counts each finished face separately. Do not add them together.
A75: Foundation trace: house perimeter, garage perimeter excluding shared segment, master-bedroom bearing line, and two exposed porch sides. Other partitions show no continuous footing hatch.
A76: S-1 footing legend is 12 in x 24 in with (2) #4 top and (2) #4 bottom. Two P2.0 pads are 2 ft x 2 ft x 24 in with (6) #5 bars bottom each way.
A77: Footing and slab concrete are reported separately as gross volumes. Their intersection, pad overlap, grade elevations and Hardy Frame anchorage can change pour totals. No combined pour total is given.
A78: Roof projection includes overhangs, porch and the east side roof extension shown on A-5. A-4 width calibrates the trace. Verify extension footprint before purchase.
A79: Roof trace at 0.6 PDF render: vertices (770,209),(1148,209),(1148,328),(1193,328),(1193,599),(1204,599),(1204,837),(966,837),(966,669),(887,669),(887,621),(770,621). Calibration: 353 px = 33 ft.
A80: A-5 roof vent note calls for four vents with 2.22 SF each. A-5 labels 16 x 20 in; A-6 labels 12 x 18 in. Verify clear net free area and actual vent sizes.
... A91: No framing lumber piece order, roof connector schedule, reinforcing lap / hook schedule, utility connection length or fire sprinkler design is inferred from the area takeoff.
